{"title":"מציג תצלומים מכוונים","currentFootprint":"עקבה נוכחית","additionalFootprints":"עקבות נוספות","additionalCameraLocations":"מיקומי מצלמות נוספים","imageAttributes":"מאפייני תמונה","imageEnhancement":"שיפור תמונה","imageGallery":"גלריית תמונות","float":"צף","dock":"מעוגן","footprint":"עקבה","noImageError":"אין תמונה זמינה עבור המיקום שנבחר.","onLoadMessage":"בחר מיקום במפה כדי לצפות בתצלומים.","imageLoadError":"אירעה שגיאה בזמן טעינת התמונה.","mapImageConversionTool":"כלי מיקום מפה-תמונה","brightness":"בהירות","contrast":"ניגודיות","sharpness":"חדות","navigationTool":"כלי ניווט","noLocalPort":"לא סופק ערך עבור יציאה מקומית. נדרשת יציאה מקומית כדי לטעון תמונות מקומיות.","noAttachment":"אין תמונה או פריט מצורף זמינים עבור המיקום שנבחר.","currentFootprintTooltip":"החלף את מצב הניראות של עקבת התמונה המוצגת.","additionalFootprintsTooltip":"החלף את מצב הניראות של כל העקבות הנוספות שמכילות את מיקום העניין.","additionalCameraLocationsTooltip":"החלף את מצב הניראות של כל מיקומי המצלמה הנוספים של תמונות שמכילות את מיקום העניין.","navigationTooltip":"גלה תמונות שהוחזרו ביחס למיקום העניין.","imageEnhancementTooltip":"כוונן בהירות, ניגודיות וחדות של תמונה.","imageGalleryTooltip":"גלה תמונות ממוזערות של כל התמונות שמתארות את מיקום העניין.","mapImageConversionTooltip":"לחץ על התמונה כדי לראות היכן מיקום זה נמצא במפה, ולהיפך.","unsupportedPanoramicImageryError":"כן_Viewer currently does not support visualizing 360-degree imagery__________________________________ש."}