{"widgetLabel":"Проследяване Utility Network","widgetDescription":"Изпълним модул за проследяване в Utility Network","globalStrings":{"selectTerminalPlaceholder":"Изберете терминали","locateFeature":"Намерете","zoomToFeature":"Приближаване","clearResults":"Отхвърляне","nonSpatialObject":"Непространствен обект"},"inputsStrings":{"headerTabInputs":"Входни данни","headerStartingPoint":"Начални точки","startingPointHint":"Добавете начални точки за проследяването.","headerBarrier":"Бариери","barrierButton":"Бариера","barrierPointHint":"Добавете бариерни точки за проследяването.","barrierFilter":"Бариера за филтриране","addPointOption":"Добавяне на точка","addPointHint":"Натиснете върху картата, за да добавите точка.","removeAllPoints":"Изтриване на всички","selectTraces":"Избор на проследявания"},"tracingStrings":{"traceOperation":"Типове проследяване","runTrace":"Стартиране"},"resultsStrings":{"headerTabResults":"Резултати","resultsListOptions":"Опции","ellipsesOptions":"Опции","displayAttribute":"Показване на атрибутите","sortBy":"Сортиране по","startOverButton":"Изчистване на всички","startOverValidation":"Сигурни ли сте? Всички входни данни и резултати за проследявания ще бъдат изгубени.","highlightTrace":"Показване на графики","noSelectionResults":"Записите не могат да бъдат избрани. Вместо това, активирайте показване на графика.","viewFeatures":"Записи","selectFeatures":"Избиране на записи","graphicColor":"Цвят","functionHeader":"Функции","noValue":"Няма стойност","resultAreaHeader":"Показване на резултат за област","resultAreaBuffer":"Буфер","noFeaturesInMap":"Няма изброени записи, защото липсват на картата."},"alertsStrings":{"startingPointAlertHeader":"Липсва начална точка","startingPointAlert":"За да изпълните това проследяване, добавете начална точка.","selectTraceAlertHeader":"Не е избран тип на прoследяване","selectTraceAlert":"Изберете тип проследяване за стартиране.","NoRunAlertHeader":"Няма налични резултати","noResultsInfo":"Отидете в раздела Входни данни, за да изберете тип проследяване, добавете начална точка и натиснете върху Run (Изпълни), за да видите резултатите.","traceExecuting":"Проследяването се изпълнява...","genericResultHeader":"Резултат от проследяване","genericErrorHeader":"Възникна грешка","noAssetsFoundHeader":"Не може да се добави точка","noAssetFound":"Тази точка трябва да се пресича с обект на картата.","clearResultsAlert":"Сигурни ли сте? Всички резултати от това проследяване ще бъдат отхвърлени.","noTraceSupported":"Utility Network не може да бъде намерена или проследяването не се поддържа. Осигурете валидна Utility Network със споделени конфигурации за проследяване.","noUserExtension":"В акаунта, в който сте влезли, липсва лиценз за разширението за потребителски тип ArcGIS Utility Network.","noTerminalDefinedHeader":"Липсва терминал","noTerminalDefined":"Трябва да бъде избран поне един терминал."},"attributeStrings":{"traceId":"ИД за проследяване","traceName":"Име за проследяване","traceDescription":"Описание на проследяване","startingPoints":"Начални точки","barriers":"Бариери","username":"Потребител","version":"Версия","date":"Дата","elementCount":"Брой записи","functionResult":"Функции за проследяване","areaStatistic":"Статистика на област","globalid":"Глобален ИД","terminalid":"ИД на терминал","x":"x","y":"y"}}