{"widgetLabel":"מעקב אחר רשת תשתית","widgetDescription":"וידג'ט לביצוע מעקבים ברשת תשתית.","globalStrings":{"selectTerminalPlaceholder":"בחר מסופים","locateFeature":"Locate","zoomToFeature":"התמקדות","clearResults":"התעלם","nonSpatialObject":"אובייקט לא מרחבי"},"inputsStrings":{"headerTabInputs":"קלטים","headerStartingPoint":"נקודות התחלה","startingPointHint":"הוסף נקודות התחלה עבור המעקב.","headerBarrier":"מחסומים","barrierButton":"מחסום","barrierPointHint":"הוסף נקודות מחסום עבור המעקב.","barrierFilter":"סנן מחסומים","addPointOption":"הוסף נקודה","addPointHint":"לחץ על המפה כדי להוסיף נקודה","removeAllPoints":"הסר הכל","selectTraces":"בחר מעקבים"},"tracingStrings":{"traceOperation":"סוגי מעקב","runTrace":"הרץ"},"resultsStrings":{"headerTabResults":"תוצאות","resultsListOptions":"אפשרויות","ellipsesOptions":"אפשרויות","displayAttribute":"הצג מאפיין","sortBy":"מיון לפי","startOverButton":"נקה הכול","startOverValidation":"האם אתה בטוח? כל הקלטים והתוצאות של המעקב יאבדו.","highlightTrace":"הצג גרפיקה","noSelectionResults":"לא ניתן לבחור את הרשומות. אפשר הצגת גרפיקה במקום זאת.","viewFeatures":"רשומות","selectFeatures":"בחירת רשומות","graphicColor":"צבע","functionHeader":"פונקציות","noValue":"ללא ערך","resultAreaHeader":"הצג אזור תוצאות","resultAreaBuffer":"חיץ","noFeaturesInMap":"לא מופיעות רשומות משום שהן לא נכללות במפה."},"alertsStrings":{"startingPointAlertHeader":"נקודת התחלה חסרה","startingPointAlert":"הוסף נקודת התחלה כדי להריץ מעקב זה.","selectTraceAlertHeader":"סוג מעקב לא נבחר","selectTraceAlert":"בחר סוג מעקב להרצה.","NoRunAlertHeader":"אין תוצאות זמינות","noResultsInfo":"עבור אל הכרטיסייה 'קלטים' כדי לבחור סוג מעקב, הוסף נקודת התחלה ולחץ על 'הפעל' כדי להציג את התוצאות.","traceExecuting":"מתבצע מעקב...","genericResultHeader":"תוצאת מעקב","genericErrorHeader":"אירעה שגיאה","noAssetsFoundHeader":"לא ניתן להוסיף נקודה","noAssetFound":"הנקודה חייבת להצטלב עם ישות במפה.","clearResultsAlert":"האם אתה בטוח? כל התוצאות עבור מעקב זה יימחקו.","noTraceSupported":"לא נמצאה Utility Network או שהמעקב לא נתמך. ציין Utility Network חוקית עם תצורות מעקב משותפות.","noUserExtension":"לחשבון המחובר חסר רישיון עבור הרחבת סוג משתמש של ArcGIS Utility Network.","noTerminalDefinedHeader":"מסוף חסר","noTerminalDefined":"יש לבחור מסוף אחד לפחות."},"attributeStrings":{"traceId":"מזהה מעקב","traceName":"שם מעקב","traceDescription":"תיאור מעקב","startingPoints":"נקודות התחלה","barriers":"מחסומים","username":"משתמש","version":"גרסה","date":"תאריך","elementCount":"מספר רשומות","functionResult":"פונקציות מעקב","areaStatistic":"סטטיסטיקת שטח","globalid":"מזהה גלובלי","terminalid":"מזהה מסוף","x":"x","y":"y"}}