{"widgetLabel":"Utility Network Trace","widgetDescription":"Ένα widget για την εκτέλεση ιχνηλάτησης σε Utility Network.","globalStrings":{"selectTerminalPlaceholder":"Επιλογή τερματικών","locateFeature":"Εντοπισμός","zoomToFeature":"Εστίαση","clearResults":"Απόρριψη","nonSpatialObject":"Μη χωρικό αντικείμενο"},"inputsStrings":{"headerTabInputs":"Εισαγωγές","headerStartingPoint":"Σημεία έναρξης","startingPointHint":"Προσθήκη σημείων έναρξης για την ιχνηλάτηση.","headerBarrier":"Φράγματα","barrierButton":"Φράγμα","barrierPointHint":"Προσθήκη σημείων φραγμάτων για την ιχνηλάτηση.","barrierFilter":"Φιλτράρισμα φραγμάτων","addPointOption":"Προσθήκη σημείου","addPointHint":"Κάντε κλικ στον χάρτη για προσθήκη σημείου","removeAllPoints":"Κατάργηση όλων","selectTraces":"Επιλογή ιχνών"},"tracingStrings":{"traceOperation":"Τύποι ιχνηλάτησης","runTrace":"Εκτέλεση"},"resultsStrings":{"headerTabResults":"Αποτελέσματα","resultsListOptions":"Επιλογές","ellipsesOptions":"Επιλογές","displayAttribute":"Προβολή χαρακτηριστικού στην οθόνη","sortBy":"Ταξινόμηση κατά","startOverButton":"Απαλοιφή όλων","startOverValidation":"Είστε βέβαιοι; Όλες οι εισαγωγές ιχνών και αποτελεσμάτων θα χαθούν.","highlightTrace":"Εμφάνιση γραφικών","noSelectionResults":"Οι εγγραφές δεν μπόρεσαν να επιλεχθούν Ενεργοποιήστε την εμφάνιση γραφικών.","viewFeatures":"Εγγραφές","selectFeatures":"Επιλογή εγγραφών","graphicColor":"Χρώμα","functionHeader":"Συναρτήσεις","noValue":"Καμία τιμή","resultAreaHeader":"Εμφάνιση περιοχής αποτελεσμάτων","resultAreaBuffer":"Ζώνη","noFeaturesInMap":"Καμία εγγραφή δεν υπάρχει στη λίστα γιατί όλες λείπουν από τον χάρτη."},"alertsStrings":{"startingPointAlertHeader":"Λείπει το σημείο έναρξης","startingPointAlert":"Προσθέστε ένα σημείο έναρξης για να εκτελέσετε αυτή την ιχνηλάτηση.","selectTraceAlertHeader":"Δεν έχει επιλεχθεί τύπος ίχνους","selectTraceAlert":"Επιλέξτε έναν τύπο ίχνους για εκτέλεση.","NoRunAlertHeader":"Δεν υπάρχουν διαθέσιμα αποτελέσματα","noResultsInfo":"Μεταβείτε στην καρτέλα Εισαγωγές για να επιλέξετε τύπο ίχνους, προσθέστε ένα σημείο έναρξης και κάντε κλικ στην επιλογή Εκτέλεση για να δείτε τα αποτελέσματα.","traceExecuting":"Ιχνηλάτηση σε εξέλιξη...","genericResultHeader":"Αποτέλεσμα ιχνηλάτησης","genericErrorHeader":"Παρουσιάστηκε σφάλμα","noAssetsFoundHeader":"Δεν είναι δυνατή η προσθήκη σημείου","noAssetFound":"Το σημείο πρέπει να τέμνεται με ένα στοιχείο στο χάρτη.","clearResultsAlert":"Είστε βέβαιοι; Όλα τα αποτελέσματα για αυτό το ίχνος θα απορριφθούν.","noTraceSupported":"Δεν είναι δυνατή η εύρεση utility network ή δεν υποστηρίζεται η ιχνηλάτηση. Καταχωρίστε ένα έγκυρο utility network με κοινοποιημένες διαμορφώσεις ιχνηλάτησης.","noUserExtension":"Στον λογαριασμό που είναι συνδεδεμένος λείπει άδεια χρήσης της επέκτασης τύπου χρήστη ArcGIS Utility Network.","noTerminalDefinedHeader":"Λείπει το τερματικό","noTerminalDefined":"Πρέπει να επιλεγεί τουλάχιστον ένα τερματικό."},"attributeStrings":{"traceId":"Id ιχνηλάτησης","traceName":"Όνομα ιχνηλάτησης","traceDescription":"Περιγραφή ιχνηλάτησης","startingPoints":"Σημεία έναρξης","barriers":"Φράγματα","username":"Χρήστης","version":"Έκδοση","date":"Ημερομηνία","elementCount":"Μέτρηση εγγραφών","functionResult":"Λειτουργίες ιχνηλάτησης","areaStatistic":"Στατιστικό στοιχείο περιοχής","globalid":"Καθολικό αναγνωριστικό","terminalid":"Αναγνωριστικό τερματικού","x":"x","y":"y"}}